tls/__init__.py
tls/util.py
tls/lib/__init__.py
tls/lib/constants.py
tls/lib/types.py
pylibtls-0.1.1.dist-info/LICENSE
pylibtls-0.1.1.dist-info/WHEEL
pylibtls-0.1.1.dist-info/METADATA
pylibtls-0.1.1.dist-info/RECORD
