Metadata-Version: 2.1
Name: pylibtls
Version: 0.1.1
Summary: pylibtls - Python bindings for libtls
Author-email: David Stenwall <david@stenwall.io>
Classifier: License :: OSI Approved :: MIT License
Requires-Dist: pytest ; extra == "test"
Requires-Dist: pytest-cov ; extra == "test"
Project-URL: GitHub, https://github.com/dafvid/pylibtls
Provides-Extra: test
